{
  "history_labels": [
    "03-06",
    "03-09",
    "03-10",
    "03-11",
    "03-12",
    "03-13",
    "03-16",
    "03-17",
    "03-18",
    "03-19"
  ],
  "whale_data": [
    {
      "name": "元富證券",
      "values": [
        87.0,
        47.0,
        164.0,
        6129.1,
        6305.9,
        6443.4,
        6279.2,
        6343.9,
        6758.9,
        6894.5
      ],
      "color": "#FF6384"
    },
    {
      "name": "兆豐新竹",
      "values": [
        -91.1,
        47.9,
        698.3,
        1176.2,
        1405.3,
        2198.9,
        3690.2,
        5048.2,
        6125.9,
        7470.9
      ],
      "color": "#36A2EB"
    },
    {
      "name": "富邦",
      "values": [
        20492.7,
        26389.0,
        23113.2,
        31231.5,
        28202.7,
        8063.5,
        6615.6,
        6830.7,
        6592.8,
        6571.5
      ],
      "color": "#FFCE56"
    },
    {
      "name": "康和",
      "values": [
        585.0,
        542.0,
        20.0,
        661.0,
        1506.0,
        -180.0,
        -165.4,
        434.6,
        5536.6,
        5323.6
      ],
      "color": "#4BC0C0"
    },
    {
      "name": "摩根大通",
      "values": [
        6435.0,
        18203.0,
        16045.0,
        46401.0,
        64849.0,
        50527.0,
        46291.8,
        59591.8,
        58093.2,
        53082.2
      ],
      "color": "#9966FF"
    },
    {
      "name": "美商高盛",
      "values": [
        5449.5,
        4787.5,
        7880.5,
        33578.5,
        85659.5,
        88207.5,
        53110.8,
        53395.8,
        43427.8,
        37488.8
      ],
      "color": "#FF9F40"
    }
  ],
  "total_whale_values": [
    32958.2,
    50016.4,
    47921.0,
    119177.3,
    187928.4,
    155260.3,
    115822.1,
    131644.9,
    126535.1,
    116831.5
  ],
  "top6_details": [
    {
      "broker_id": "8440",
      "broker_name": "摩根大通",
      "net_10d": 53082.2,
      "net_5d": -11766.8,
      "net_1d": -5011.0,
      "avg_price": 15.44,
      "city": "台北市",
      "broker_org_type": "foreign",
      "is_proprietary": "",
      "seat_type": "hq",
      "streak_buy": 0,
      "streak_sell": 2,
      "archetype_wave_score": 0.62,
      "archetype_label": "mixed",
      "km_to_hq": 62.4
    },
    {
      "broker_id": "1480",
      "broker_name": "美商高盛",
      "net_10d": 37488.8,
      "net_5d": -48170.7,
      "net_1d": -5939.0,
      "avg_price": 15.42,
      "city": "台北市",
      "broker_org_type": "foreign",
      "is_proprietary": "",
      "seat_type": "hq",
      "streak_buy": 0,
      "streak_sell": 2,
      "archetype_wave_score": 0.62,
      "archetype_label": "mixed",
      "km_to_hq": 60.8
    },
    {
      "broker_id": "700V",
      "broker_name": "兆豐新竹",
      "net_10d": 7470.9,
      "net_5d": 6065.6,
      "net_1d": 1345.0,
      "avg_price": 15.79,
      "city": "新竹市",
      "broker_org_type": "local",
      "is_proprietary": "",
      "seat_type": "branch",
      "streak_buy": 9,
      "streak_sell": 0,
      "archetype_wave_score": 0.97,
      "archetype_label": "swing_leader",
      "km_to_hq": 6.6
    },
    {
      "broker_id": "9B00",
      "broker_name": "元富證券",
      "net_10d": 6894.5,
      "net_5d": 588.6,
      "net_1d": 135.6,
      "avg_price": 16.34,
      "city": "",
      "broker_org_type": "unknown",
      "is_proprietary": "",
      "seat_type": "",
      "streak_buy": 3,
      "streak_sell": 0,
      "archetype_wave_score": 0.79,
      "archetype_label": "swing_leader",
      "km_to_hq": null
    },
    {
      "broker_id": "9600",
      "broker_name": "富邦",
      "net_10d": 6571.5,
      "net_5d": -21631.1,
      "net_1d": -21.2,
      "avg_price": 15.75,
      "city": "台北市",
      "broker_org_type": "local",
      "is_proprietary": "",
      "seat_type": "hq",
      "streak_buy": 0,
      "streak_sell": 2,
      "archetype_wave_score": 0.62,
      "archetype_label": "mixed",
      "km_to_hq": 61.4
    },
    {
      "broker_id": "8450",
      "broker_name": "康和",
      "net_10d": 5323.6,
      "net_5d": 3817.6,
      "net_1d": -213.0,
      "avg_price": 15.94,
      "city": "台北市",
      "broker_org_type": "local",
      "is_proprietary": "",
      "seat_type": "hq",
      "streak_buy": 0,
      "streak_sell": 1,
      "archetype_wave_score": 0.66,
      "archetype_label": "mixed",
      "km_to_hq": 62.7
    }
  ],
  "signals": {
    "concentration_5d": 9.88,
    "concentration_20d": 5.98,
    "netbuy_1d_lot": 0.0,
    "netbuy_5d_lot": -994.0,
    "netbuy_20d_lot": -4426.0,
    "buy_count_5d": 686,
    "sell_count_5d": 128,
    "breadth_5d": 558,
    "breadth_ratio_5d": 0.8428,
    "buy_count_20d": 657,
    "sell_count_20d": 208,
    "breadth_20d": 449,
    "breadth_ratio_20d": 0.7595,
    "foreign_net_5d": -151189051.0,
    "local_net_5d": 144837283.0,
    "top_buy_15": [
      {
        "broker_id": "8880",
        "broker_name": "國泰綜合",
        "net_lot": 83182.4,
        "city": "台北市",
        "broker_org_type": "local",
        "streak_buy": 0,
        "streak_sell": 1
      },
      {
        "broker_id": "8888",
        "broker_name": "國泰敦南",
        "net_lot": 35637.7,
        "city": "台北市",
        "broker_org_type": "local",
        "streak_buy": 1,
        "streak_sell": 0
      },
      {
        "broker_id": "9A00",
        "broker_name": "永豐金",
        "net_lot": 22652.2,
        "city": "台北市",
        "broker_org_type": "local",
        "streak_buy": 0,
        "streak_sell": 1
      },
      {
        "broker_id": "779c",
        "broker_name": "國票敦北",
        "net_lot": 11195.6,
        "city": "台北市",
        "broker_org_type": "local",
        "streak_buy": 5,
        "streak_sell": 0
      },
      {
        "broker_id": "700V",
        "broker_name": "兆豐新竹",
        "net_lot": 9130.2,
        "city": "新竹市",
        "broker_org_type": "local",
        "streak_buy": 9,
        "streak_sell": 0
      },
      {
        "broker_id": "9B00",
        "broker_name": "元富證券",
        "net_lot": 7805.6,
        "city": "",
        "broker_org_type": "unknown",
        "streak_buy": 3,
        "streak_sell": 0
      },
      {
        "broker_id": "9667",
        "broker_name": "富邦台南",
        "net_lot": 7265.8,
        "city": "台南市",
        "broker_org_type": "local",
        "streak_buy": 2,
        "streak_sell": 0
      },
      {
        "broker_id": "961R",
        "broker_name": "富邦南員",
        "net_lot": 6711.4,
        "city": "彰化縣",
        "broker_org_type": "local",
        "streak_buy": 2,
        "streak_sell": 0
      },
      {
        "broker_id": "961H",
        "broker_name": "富邦新板",
        "net_lot": 6065.5,
        "city": "新北市",
        "broker_org_type": "local",
        "streak_buy": 0,
        "streak_sell": 1
      },
      {
        "broker_id": "9A9W",
        "broker_name": "永豐市政",
        "net_lot": 5952.7,
        "city": "台中市",
        "broker_org_type": "local",
        "streak_buy": 6,
        "streak_sell": 0
      },
      {
        "broker_id": "8882",
        "broker_name": "國泰台中",
        "net_lot": 5869.2,
        "city": "台中市",
        "broker_org_type": "local",
        "streak_buy": 1,
        "streak_sell": 0
      },
      {
        "broker_id": "6462",
        "broker_name": "大昌安康",
        "net_lot": 5864.4,
        "city": "新北市",
        "broker_org_type": "local",
        "streak_buy": 1,
        "streak_sell": 0
      },
      {
        "broker_id": "8450",
        "broker_name": "康和",
        "net_lot": 5671.4,
        "city": "台北市",
        "broker_org_type": "local",
        "streak_buy": 0,
        "streak_sell": 1
      },
      {
        "broker_id": "9A9j",
        "broker_name": "永豐嘉義",
        "net_lot": 5596.8,
        "city": "嘉義市",
        "broker_org_type": "local",
        "streak_buy": 9,
        "streak_sell": 0
      },
      {
        "broker_id": "6168",
        "broker_name": "中信嘉義",
        "net_lot": 5437.1,
        "city": "嘉義市",
        "broker_org_type": "local",
        "streak_buy": 0,
        "streak_sell": 1
      }
    ],
    "top_sell_15": [
      {
        "broker_id": "9800",
        "broker_name": "元大",
        "net_lot": -116518.4,
        "city": "台北市",
        "broker_org_type": "local",
        "streak_buy": 3,
        "streak_sell": 0
      },
      {
        "broker_id": "1470",
        "broker_name": "台灣摩根",
        "net_lot": -110935.3,
        "city": "台北市",
        "broker_org_type": "foreign",
        "streak_buy": 0,
        "streak_sell": 2
      },
      {
        "broker_id": "8440",
        "broker_name": "摩根大通",
        "net_lot": -99250.7,
        "city": "台北市",
        "broker_org_type": "foreign",
        "streak_buy": 0,
        "streak_sell": 2
      },
      {
        "broker_id": "1440",
        "broker_name": "美林",
        "net_lot": -62249.4,
        "city": "台北市",
        "broker_org_type": "foreign",
        "streak_buy": 0,
        "streak_sell": 1
      },
      {
        "broker_id": "9600",
        "broker_name": "富邦",
        "net_lot": -58940.1,
        "city": "台北市",
        "broker_org_type": "local",
        "streak_buy": 0,
        "streak_sell": 2
      },
      {
        "broker_id": "1650",
        "broker_name": "瑞銀",
        "net_lot": -53241.3,
        "city": "台北市",
        "broker_org_type": "foreign",
        "streak_buy": 0,
        "streak_sell": 2
      },
      {
        "broker_id": "1480",
        "broker_name": "美商高盛",
        "net_lot": -47578.5,
        "city": "台北市",
        "broker_org_type": "foreign",
        "streak_buy": 0,
        "streak_sell": 2
      },
      {
        "broker_id": "1590",
        "broker_name": "花旗環球",
        "net_lot": -36846.8,
        "city": "台北市",
        "broker_org_type": "foreign",
        "streak_buy": 0,
        "streak_sell": 2
      },
      {
        "broker_id": "1560",
        "broker_name": "港商野村",
        "net_lot": -29321.2,
        "city": "台北市",
        "broker_org_type": "foreign",
        "streak_buy": 0,
        "streak_sell": 2
      },
      {
        "broker_id": "1360",
        "broker_name": "港麥格理",
        "net_lot": -21565.1,
        "city": "台北市",
        "broker_org_type": "foreign",
        "streak_buy": 1,
        "streak_sell": 0
      },
      {
        "broker_id": "5850",
        "broker_name": "統一",
        "net_lot": -15628.8,
        "city": "台北市",
        "broker_org_type": "local",
        "streak_buy": 0,
        "streak_sell": 1
      },
      {
        "broker_id": "9268",
        "broker_name": "凱基台北",
        "net_lot": -12464.7,
        "city": "台北市",
        "broker_org_type": "local",
        "streak_buy": 0,
        "streak_sell": 2
      },
      {
        "broker_id": "9200",
        "broker_name": "凱基",
        "net_lot": -12303.4,
        "city": "台北市",
        "broker_org_type": "local",
        "streak_buy": 0,
        "streak_sell": 2
      },
      {
        "broker_id": "6160",
        "broker_name": "中國信託",
        "net_lot": -11662.1,
        "city": "台北市",
        "broker_org_type": "local",
        "streak_buy": 1,
        "streak_sell": 0
      },
      {
        "broker_id": "7000",
        "broker_name": "兆豐",
        "net_lot": -7964.9,
        "city": "台北市",
        "broker_org_type": "local",
        "streak_buy": 1,
        "streak_sell": 0
      }
    ],
    "labels_20d": [
      "12-12",
      "12-15",
      "12-16",
      "12-17",
      "12-18",
      "12-19",
      "12-22",
      "12-23",
      "12-24",
      "12-26",
      "12-29",
      "12-30",
      "12-31",
      "01-02",
      "01-05",
      "01-06",
      "01-07",
      "01-08",
      "01-09",
      "01-12",
      "01-13",
      "01-14",
      "01-15",
      "01-16",
      "01-19",
      "01-20",
      "01-21",
      "01-22",
      "01-23",
      "01-26",
      "01-27",
      "01-28",
      "01-29",
      "01-30",
      "02-02",
      "02-03",
      "02-04",
      "02-05",
      "02-06",
      "02-09",
      "02-10",
      "02-11",
      "02-23",
      "02-24",
      "02-25",
      "02-26",
      "03-02",
      "03-03",
      "03-04",
      "03-05",
      "03-06",
      "03-09",
      "03-10",
      "03-11",
      "03-12",
      "03-13",
      "03-16",
      "03-17",
      "03-18",
      "03-19"
    ],
    "buy_count_series_20d": [
      518,
      261,
      533,
      481,
      620,
      459,
      431,
      564,
      404,
      545,
      555,
      563,
      453,
      249,
      210,
      390,
      417,
      659,
      528,
      657,
      577,
      588,
      531,
      244,
      165,
      659,
      635,
      671,
      387,
      518,
      609,
      599,
      360,
      609,
      536,
      342,
      183,
      632,
      505,
      581,
      347,
      128,
      587,
      186,
      449,
      174,
      166,
      676,
      485,
      553,
      161,
      434,
      524,
      124,
      209,
      653,
      720,
      285,
      417,
      600
    ],
    "sell_count_series_20d": [
      147,
      381,
      143,
      198,
      117,
      226,
      263,
      187,
      335,
      189,
      250,
      240,
      355,
      552,
      597,
      421,
      398,
      155,
      283,
      155,
      236,
      224,
      277,
      565,
      649,
      157,
      180,
      141,
      421,
      282,
      201,
      209,
      452,
      199,
      264,
      450,
      623,
      182,
      307,
      225,
      449,
      685,
      226,
      625,
      362,
      636,
      647,
      136,
      323,
      251,
      645,
      368,
      280,
      687,
      601,
      159,
      90,
      520,
      382,
      202
    ],
    "breadth_series_20d": [
      371,
      -120,
      390,
      283,
      503,
      233,
      168,
      377,
      69,
      356,
      305,
      323,
      98,
      -303,
      -387,
      -31,
      19,
      504,
      245,
      502,
      341,
      364,
      254,
      -321,
      -484,
      502,
      455,
      530,
      -34,
      236,
      408,
      390,
      -92,
      410,
      272,
      -108,
      -440,
      450,
      198,
      356,
      -102,
      -557,
      361,
      -439,
      87,
      -462,
      -481,
      540,
      162,
      302,
      -484,
      66,
      244,
      -563,
      -392,
      494,
      630,
      -235,
      35,
      398
    ],
    "breadth_ratio_series_20d": [
      0.7789,
      0.4065,
      0.7885,
      0.7084,
      0.8412,
      0.6701,
      0.621,
      0.751,
      0.5467,
      0.7425,
      0.6894,
      0.7011,
      0.5606,
      0.3109,
      0.2602,
      0.4809,
      0.5117,
      0.8096,
      0.651,
      0.8091,
      0.7097,
      0.7241,
      0.6572,
      0.3016,
      0.2027,
      0.8076,
      0.7791,
      0.8264,
      0.479,
      0.6475,
      0.7519,
      0.7413,
      0.4433,
      0.7537,
      0.67,
      0.4318,
      0.227,
      0.7764,
      0.6219,
      0.7208,
      0.4359,
      0.1574,
      0.722,
      0.2293,
      0.5536,
      0.2148,
      0.2042,
      0.8325,
      0.6002,
      0.6878,
      0.1998,
      0.5411,
      0.6517,
      0.1529,
      0.258,
      0.8042,
      0.8889,
      0.354,
      0.5219,
      0.7481
    ],
    "inst_foreign_net_5d": -183405037.0,
    "inst_trust_net_5d": -6325000.0,
    "inst_three_net_5d": -187488486.0,
    "inst_foreign_net_20d": 225992183.0,
    "inst_trust_net_20d": -4899913.0,
    "inst_three_net_20d": 233345485.0,
    "inst_foreign_net_60d": -90025703.0,
    "inst_trust_net_60d": -24333354.0,
    "inst_three_net_60d": -112309946.0,
    "inst_three_align_5d": 0,
    "margin_balance_20d_change": -0.0631,
    "margin_risk_flag": 0,
    "sbl_volume_5d": 7269.0,
    "sbl_volume_20d": 30291.0,
    "sbl_volume_60d": 162027.0,
    "sbl_volume_series_60d": [
      407.0,
      11.0,
      29.0,
      31.0,
      38.0,
      52.0,
      4.0,
      1000.0,
      29505.0,
      60.0,
      635.0,
      600.0,
      195.0,
      1000.0,
      6.0,
      49.0,
      22.0,
      20000.0,
      34632.0,
      195.0,
      7.0,
      3.0,
      42.0,
      2.0,
      180.0,
      416.0,
      10621.0,
      12162.0,
      700.0,
      1500.0,
      126.0,
      1000.0,
      1621.0,
      21.0,
      7.0,
      970.0,
      149.0,
      600.0,
      10164.0,
      2974.0,
      798.0,
      1000.0,
      250.0,
      173.0,
      2000.0,
      2586.0,
      3644.0,
      5000.0,
      3000.0,
      650.0,
      1500.0,
      71.0,
      150.0,
      1000.0,
      1200.0,
      19.0,
      50.0,
      74.0,
      7000.0,
      126.0
    ],
    "sbl_labels_60d": [
      "03-10",
      "03-10",
      "03-10",
      "03-10",
      "03-10",
      "03-10",
      "03-11",
      "03-11",
      "03-11",
      "03-11",
      "03-11",
      "03-11",
      "03-12",
      "03-12",
      "03-12",
      "03-13",
      "03-13",
      "03-13",
      "03-13",
      "03-13",
      "03-13",
      "03-13",
      "03-13",
      "03-13",
      "03-13",
      "03-13",
      "03-13",
      "03-13",
      "03-13",
      "03-13",
      "03-13",
      "03-13",
      "03-13",
      "03-16",
      "03-16",
      "03-16",
      "03-16",
      "03-16",
      "03-16",
      "03-16",
      "03-16",
      "03-16",
      "03-16",
      "03-16",
      "03-17",
      "03-17",
      "03-17",
      "03-17",
      "03-17",
      "03-17",
      "03-17",
      "03-17",
      "03-17",
      "03-17",
      "03-18",
      "03-18",
      "03-18",
      "03-19",
      "03-19",
      "03-19"
    ],
    "sbl_short_pressure_ratio_20d": 0.561,
    "sbl_short_pressure_flag": 0,
    "inst_bull_no_short_pressure_flag": 1,
    "inst_bear_with_short_pressure_flag": 0,
    "top6_avg_wave_score": 0.713,
    "top6_max_wave_score": 0.97,
    "top6_wave_leader_id": "700V",
    "top6_wave_leader_name": "兆豐新竹",
    "delta_major_flow_20": -472432.7,
    "top15_buy_sum_20": 224038.0,
    "top15_sell_sum_20": 696470.7,
    "delta_major_flow_5": -156131.0,
    "top15_buy_sum_5": 47533.8,
    "top15_sell_sum_5": 203664.8,
    "pressure_ratio_20d": 0.2434,
    "net_pressure_20d": -0.5132,
    "pressure_ratio_5d": 0.1892,
    "net_pressure_5d": -0.6215,
    "top15_buy_stability_20d": 0.0872,
    "top15_buy_stability_10d": 0.1051,
    "top15_buy_avg_size_10d": 15.0,
    "turning_points": {
      "foreign_buy_switch": 0,
      "local_buy_switch": 0,
      "whale_reversal": 0,
      "abnormal_buy_spike": 1,
      "cost_zone_defended": 1
    },
    "whale_radar": {
      "labels": [
        "集中度",
        "淨買方向",
        "買盤廣度",
        "外本協同",
        "短期加速"
      ],
      "values": [
        6.0,
        14.2,
        84.3,
        70.0,
        50.0
      ],
      "debug": {
        "c20": 5.98,
        "net1": 0.0,
        "net5": -994.0,
        "net20": -4426.0,
        "scale": 1106.5,
        "breadth_ratio_5d": 0.8428,
        "foreign_5d": -151189051.0,
        "local_5d": 144837283.0,
        "same_sign": 0,
        "avg5": -198.8,
        "den": 198.8
      }
    },
    "enhanced": {
      "coherence_today": 1.32,
      "buy_cnt_today": 600,
      "avg_buy_cnt_20d": 455.1,
      "coherence_series_20d": [
        1.14,
        0.57,
        1.17,
        1.06,
        1.36,
        1.01,
        0.95,
        1.24,
        0.89,
        1.2,
        1.22,
        1.24,
        1.0,
        0.55,
        0.46,
        0.86,
        0.92,
        1.45,
        1.16,
        1.44,
        1.27,
        1.29,
        1.17,
        0.54,
        0.36,
        1.45,
        1.4,
        1.47,
        0.85,
        1.14,
        1.34,
        1.32,
        0.79,
        1.34,
        1.18,
        0.75,
        0.4,
        1.39,
        1.11,
        1.28,
        0.76,
        0.28,
        1.29,
        0.41,
        0.99,
        0.38,
        0.36,
        1.49,
        1.07,
        1.22,
        0.35,
        0.95,
        1.15,
        0.27,
        0.46,
        1.43,
        1.58,
        0.63,
        0.92,
        1.32
      ],
      "coherence_slope_5d": -0.088,
      "coherence_persistence_20d": 0.383,
      "coherence_max_20d": 1.58,
      "cost_low": 15.42,
      "cost_high": 16.34,
      "close_last": 15.75,
      "cost_deviation": 0.021,
      "cost_zone_status": "inside_zone",
      "cz_touch_20d": 15,
      "cz_break_up_20d": 5,
      "cz_break_dn_20d": 4,
      "cz_defense_win_20d": 14,
      "cz_defense_rate_20d": 0.389,
      "streak_strength": 0.0
    },
    "regime_score": 65,
    "regime_trend": "transition",
    "regime_tags": [
      "ma20>ma60",
      "ma60_up",
      "inside_120d_range",
      "atr_high",
      "regime_transition"
    ],
    "sig_vwap": 1,
    "sig_accumulation": 0,
    "sig_rotation": 0,
    "sig_profile_zone": 0,
    "sig_structure_break": 0,
    "tv_score": 1,
    "tv_grade": "weak",
    "trend_score": 56.0,
    "trend": "震盪",
    "tags": [
      "外/本分歧",
      "買盤擴散",
      "淨賣主導",
      "方向拉扯"
    ],
    "score": 56.0,
    "score_unified": 56.0,
    "validation": {
      "breakout_flag": 0,
      "divergence_flag": 0,
      "confirmation_score": 22.4
    },
    "risk": {
      "atr_pct_20d": 0.0644,
      "avg_turnover_20d": 4482962806.4825,
      "invalid_flag": 1
    },
    "breakout_flag": 0,
    "divergence_flag": 0,
    "confirmation_score": 22.4,
    "atr_pct_20d": 0.0644,
    "avg_turnover_20d": 4482962806.4825,
    "invalid_flag": 1,
    "geo_top5_avg_km": 49.5,
    "geo_top5_min_km": 6.6,
    "geo_top5_wavg_km": 57.1,
    "geo_affinity_score": 46.7,
    "geo_top5_detail": [
      {
        "broker_id": "8880",
        "broker_name": "國泰綜合",
        "net_lot": 83182.4,
        "km_to_hq": 60.3
      },
      {
        "broker_id": "8888",
        "broker_name": "國泰敦南",
        "net_lot": 35637.7,
        "km_to_hq": 60.2
      },
      {
        "broker_id": "9A00",
        "broker_name": "永豐金",
        "net_lot": 22652.2,
        "km_to_hq": 58.5
      },
      {
        "broker_id": "779c",
        "broker_name": "國票敦北",
        "net_lot": 11195.6,
        "km_to_hq": 61.8
      },
      {
        "broker_id": "700V",
        "broker_name": "兆豐新竹",
        "net_lot": 9130.2,
        "km_to_hq": 6.6
      }
    ],
    "geo_zscore": -1.54,
    "geo_baseline_mu_km": 61.1,
    "geo_baseline_sd_km": 2.6,
    "geo_baseline_n": 271,
    "geo_baseline_tag": "baseline_org_city:local_台北市",
    "geo_baseline_weight": 1.0,
    "geo_grade": "C",
    "geo_tag": "geo_far_boost_z|baseline_org_city:local_台北市",
    "buy_hhi_20d": 0.1854,
    "buy_entropy_20d": 2.1657,
    "sell_hhi_20d": 0.1064,
    "sell_entropy_20d": 2.4187,
    "dist_risk_flag": 0,
    "dist_risk_tag": "",
    "monitor_state": "FADING",
    "monitor_reasons": [
      "pressure_sell_dominate",
      "coherence_fading"
    ],
    "final_score": 59.6,
    "final_grade": "C",
    "weights": {
      "whale": 0.6,
      "regime": 0.4
    },
    "geo_adjust": 1.0,
    "chip_score": 34.6,
    "chip_light": "red",
    "chip_comment": "目前籌碼較不友善（主力偏保守或資金較分散），建議先當作次要標的或等待型態改善。"
  },
  "stock_id": "2409",
  "stock_name": "友達",
  "probe_date": "2026-03-19",
  "last_update": "2026-03-20 16:32"
}